ads_mcp/__init__.py
ads_mcp/coordinator.py
ads_mcp/gaql_resources.json
ads_mcp/mcp_header_interceptor.py
ads_mcp/server.py
ads_mcp/update_references.py
ads_mcp/utils.py
ads_mcp/tools/core.py
ads_mcp/tools/search.py
google_ads_mcp-0.0.1.dist-info/licenses/LICENSE
google_ads_mcp-0.0.1.dist-info/METADATA
google_ads_mcp-0.0.1.dist-info/WHEEL
google_ads_mcp-0.0.1.dist-info/entry_points.txt
google_ads_mcp-0.0.1.dist-info/top_level.txt
google_ads_mcp-0.0.1.dist-info/RECORD
