Metadata-Version: 2.4
Name: google-ads-mcp
Version: 0.0.1
Summary: MCP Server for Google Ads, depends on Google Ads API.
Author-email: Dean Lukies <lukiesd@users.noreply.github.com>
License-Expression: Apache-2.0
Project-URL: homepage, https://github.com/googleads/google-ads-mcp
Project-URL: repository, https://github.com/googleads/google-ads-mcp.git
Project-URL: issues, https://github.com/googleads/google-ads-mcp/issues
Keywords: Google Ads,Google Ads API,MCP
Classifier: Intended Audience :: Developers
Classifier: Intended Audience :: End Users/Desktop
Classifier: Programming Language :: Python
Requires-Python: >=3.10
License-File: LICENSE
Requires-Dist: google-ads>=28.0.0
Requires-Dist: mcp[cli]>=1.2.0
Provides-Extra: dev
Requires-Dist: black; extra == "dev"
Requires-Dist: nox<2026,>=2025.5.1; extra == "dev"
Dynamic: license-file
